COPYING
MANIFEST.in
README.rst
buildout.cfg
requirements.txt
setup.py
version.txt
bob/__init__.py
bob.ip.dlib.egg-info/PKG-INFO
bob.ip.dlib.egg-info/SOURCES.txt
bob.ip.dlib.egg-info/dependency_links.txt
bob.ip.dlib.egg-info/entry_points.txt
bob.ip.dlib.egg-info/requires.txt
bob.ip.dlib.egg-info/top_level.txt
bob/ip/__init__.py
bob/ip/dlib/AlignDlib.py
bob/ip/dlib/DlibLandmarkExtraction.py
bob/ip/dlib/FaceDetector.py
bob/ip/dlib/__init__.py
bob/ip/dlib/utils.py
bob/ip/dlib/data/image_r10.hdf5
bob/ip/dlib/data/multiple-faces.jpg
bob/ip/dlib/data/test_image.hdf5
bob/ip/dlib/test/__init__.py
bob/ip/dlib/test/test.py
doc/conf.py
doc/index.rst
doc/py_api.rst
doc/references.rst
doc/plot/plot_align_faces.py
doc/plot/plot_landmarks.py
doc/plot/plot_multiple_faces.py
doc/plot/plot_single_faces.py